{
	"name": "scroll-area",
	"type": "registry:ui",
	"dependencies": [
		"bits-ui"
	],
	"registryDependencies": [],
	"files": [
		{
			"name": "index.ts",
			"content": "import Scrollbar from \"./scroll-area-scrollbar.svelte\";\nimport Root from \"./scroll-area.svelte\";\n\nexport {\n\tRoot,\n\tScrollbar,\n\t//,\n\tRoot as ScrollArea,\n\tScrollbar as ScrollAreaScrollbar,\n};\n",
			"type": "registry:ui",
			"target": "scroll-area/index.ts"
		},
		{
			"name": "scroll-area-scrollbar.svelte",
			"content": "<script lang=\"ts\">\n\timport { ScrollArea as ScrollAreaPrimitive, type WithoutChild } from \"bits-ui\";\n\timport { cn } from \"$lib/utils.js\";\n\n\tlet {\n\t\tref = $bindable(null),\n\t\tclass: className,\n\t\torientation = \"vertical\",\n\t\tchildren,\n\t\t...restProps\n\t}: WithoutChild<ScrollAreaPrimitive.ScrollbarProps> = $props();\n</script>\n\n<ScrollAreaPrimitive.Scrollbar\n\t{orientation}\n\tclass={cn(\n\t\t\"flex touch-none select-none transition-colors\",\n\t\torientation === \"vertical\" && \"h-full w-2.5 border-l border-l-transparent p-px\",\n\t\torientation === \"horizontal\" && \"h-2.5 w-full border-t border-t-transparent p-px\",\n\t\tclassName\n\t)}\n\t{...restProps}\n>\n\t{@render children?.()}\n\t<ScrollAreaPrimitive.Thumb\n\t\tclass={cn(\"bg-border relative rounded-full\", orientation === \"vertical\" && \"flex-1\")}\n\t/>\n</ScrollAreaPrimitive.Scrollbar>\n",
			"type": "registry:ui",
			"target": "scroll-area/scroll-area-scrollbar.svelte"
		},
		{
			"name": "scroll-area.svelte",
			"content": "<script lang=\"ts\">\n\timport { ScrollArea as ScrollAreaPrimitive, type WithoutChild } from \"bits-ui\";\n\timport { Scrollbar } from \"./index.js\";\n\timport { cn } from \"$lib/utils.js\";\n\n\tlet {\n\t\tref = $bindable(null),\n\t\tclass: className,\n\t\torientation = \"vertical\",\n\t\tscrollbarXClasses = \"\",\n\t\tscrollbarYClasses = \"\",\n\t\tchildren,\n\t\t...restProps\n\t}: WithoutChild<ScrollAreaPrimitive.RootProps> & {\n\t\torientation?: \"vertical\" | \"horizontal\" | \"both\" | undefined;\n\t\tscrollbarXClasses?: string | undefined;\n\t\tscrollbarYClasses?: string | undefined;\n\t} = $props();\n</script>\n\n<ScrollAreaPrimitive.Root {...restProps} class={cn(\"relative overflow-hidden\", className)}>\n\t<ScrollAreaPrimitive.Viewport class=\"h-full w-full rounded-[inherit]\">\n\t\t{@render children?.()}\n\t</ScrollAreaPrimitive.Viewport>\n\t{#if orientation === \"vertical\" || orientation === \"both\"}\n\t\t<Scrollbar orientation=\"vertical\" class={scrollbarYClasses} />\n\t{/if}\n\t{#if orientation === \"horizontal\" || orientation === \"both\"}\n\t\t<Scrollbar orientation=\"horizontal\" class={scrollbarXClasses} />\n\t{/if}\n\t<ScrollAreaPrimitive.Corner />\n</ScrollAreaPrimitive.Root>\n",
			"type": "registry:ui",
			"target": "scroll-area/scroll-area.svelte"
		}
	]
}